graphlow/__init__.py
graphlow-0.0.1.dist-info/LICENSE
graphlow-0.0.1.dist-info/METADATA
graphlow-0.0.1.dist-info/WHEEL
graphlow-0.0.1.dist-info/RECORD
